{"UI": {"score": "7/7 4/7", "date": "2025-09-18", "exchange": "NYQ", "currency": "USD", "gain": 0.23471340627093246, "low_since_signal": 0.013763516315269043, "high_since_signal": 0.25543044878951227}, "PRIM": {"score": "7/7 4/7", "date": "2025-09-18", "exchange": "NYQ", "currency": "USD", "gain": 0.13015697720280836, "low_since_signal": 0.015539954247850542, "high_since_signal": 0.1379663958349767}, "IDCC": {"score": "7/7 4/7", "date": "2025-09-18", "exchange": "NMS", "currency": "USD", "gain": 0.17142772739357784, "low_since_signal": -0.012968597678059692, "high_since_signal": 0.17142772739357784}, "TPR": {"score": "7/7 4/7", "date": "2025-09-18", "exchange": "NYQ", "currency": "USD", "gain": -0.0615180935569285, "low_since_signal": -0.0615180935569285, "high_since_signal": 0.033892321270962075}, "CMPO": {"score": "7/7 4/7", "date": "2025-09-18", "exchange": "NYQ", "currency": "USD", "gain": 0.019860973187686124, "low_since_signal": -0.03475670307845081, "high_since_signal": 0.03525322740814304}, "NXT": {"score": "7/7 4/7", "date": "2025-09-18", "exchange": "NMS", "currency": "USD", "gain": 0.44012485811577745, "low_since_signal": 0.0011350737797956624, "high_since_signal": 0.4567253121452894}, "AEM": {"score": "7/7 4/7", "date": "2025-09-18", "exchange": "NYQ", "currency": "USD", "gain": 0.052662261951029896, "low_since_signal": 0.005117243166213189, "high_since_signal": 0.20171006607073466}, "WYNN": {"score": "7/7 5/7", "date": "2025-09-18", "exchange": "NMS", "currency": "USD", "gain": -0.02292508548336962, "low_since_signal": -0.12558284115635693, "high_since_signal": 0.03621386384830585}, "TBBK": {"score": "7/7 4/7", "date": "2025-09-18", "exchange": "NMS", "currency": "USD", "gain": -0.20942211055276377, "low_since_signal": -0.20942211055276377, "high_since_signal": 0.009296482412060417}, "GTX": {"score": "7/7 4/7", "date": "2025-09-18", "exchange": "NMS", "currency": "USD", "gain": 0.27654867256637156, "low_since_signal": -0.0789085545722714, "high_since_signal": 0.2853982300884955}, "PUK": {"score": "7/7 4/7", "date": "2025-09-18", "exchange": "NYQ", "currency": "USD", "gain": 0.005689900426742537, "low_since_signal": -0.0483641536273115, "high_since_signal": 0.005689900426742537}, "GSL": {"score": "7/7 4/7", "date": "2025-09-18", "exchange": "NYQ", "currency": "USD", "gain": -0.046279491833030886, "low_since_signal": -0.17090139140955843, "high_since_signal": -0.022383545069570538}, "ATGE": {"score": "7/7 4/7", "date": "2025-09-18", "exchange": "NYQ", "currency": "USD", "gain": -0.3153824119163563, "low_since_signal": -0.3153824119163563, "high_since_signal": 0.10605843597822975}, "BWA": {"score": "7/7 5/7", "date": "2025-09-18", "exchange": "NYQ", "currency": "USD", "gain": -0.013726372637263715, "low_since_signal": -0.07268226822682261, "high_since_signal": 0.006750675067506847}, "SBS": {"score": "7/7 5/7", "date": "2025-09-18", "exchange": "NYQ", "currency": "USD", "gain": 0.02050020500205002, "low_since_signal": -0.08692086920869213, "high_since_signal": 0.025010250102501002}}