{"HOOD": {"score": "7/7 4/7", "date": "2025-08-18", "exchange": "NMS", "currency": "USD", "gain": 0.08485480785950274, "low_since_signal": -0.12345679012345682, "high_since_signal": 0.08485480785950274}, "CYD": {"score": "7/7 4/7", "date": "2025-08-18", "exchange": "NYQ", "currency": "USD", "gain": 0.2918149466192171, "low_since_signal": -0.019734713684891603, "high_since_signal": 0.3267550954383694}, "KGC": {"score": "7/7 6/7", "date": "2025-08-18", "exchange": "NYQ", "currency": "USD", "gain": 0.21395348837209285, "low_since_signal": -0.03514211886304908, "high_since_signal": 0.21395348837209285}, "RYTM": {"score": "7/7 5/7", "date": "2025-08-18", "exchange": "NGM", "currency": "USD", "gain": -0.02069527984504028, "low_since_signal": -0.02630237536955855, "high_since_signal": 0.06606177999796095}, "ENLT": {"score": "7/7 5/7", "date": "2025-08-18", "exchange": "NMS", "currency": "USD", "gain": 0.058802177858439234, "low_since_signal": -0.055172413793103434, "high_since_signal": 0.0733212341197822}, "AHR": {"score": "7/7 5/7", "date": "2025-08-18", "exchange": "NYQ", "currency": "USD", "gain": 0.0327788649706457, "low_since_signal": -0.0002446183953034519, "high_since_signal": 0.055772994129158364}, "LRN": {"score": "7/7 5/7", "date": "2025-08-18", "exchange": "NYQ", "currency": "USD", "gain": -0.12863555309598468, "low_since_signal": -0.14812765172477405, "high_since_signal": 0.044149295947857145}, "BVN": {"score": "7/7 6/7", "date": "2025-08-18", "exchange": "NYQ", "currency": "USD", "gain": 0.12904967602591796, "low_since_signal": -0.017818574514038784, "high_since_signal": 0.12904967602591796}, "SEB": {"score": "7/7 5/7", "date": "2025-08-18", "exchange": "ASE", "currency": "USD", "gain": -0.021793202130692146, "low_since_signal": -0.021793202130692146, "high_since_signal": 0.12195026521863074}, "REX": {"score": "7/7 4/7", "date": "2025-08-18", "exchange": "NYQ", "currency": "USD", "gain": 0.08377706780262688, "low_since_signal": -0.0067447639332623805, "high_since_signal": 0.13809016684416048}}