{"INSM": {"score": "7/7 5/7", "date": "2025-12-01", "exchange": "NMS", "currency": "USD", "gain": -0.21219431436545094, "low_since_signal": -0.21219431436545094, "high_since_signal": -0.02190057234757105}, "ASA": {"score": "7/7 4/7", "date": "2025-12-01", "exchange": "NYQ", "currency": "USD", "gain": 0.06935123042505591, "low_since_signal": -0.029082774049217046, "high_since_signal": 0.07867263236390751}, "MGIC": {"score": "7/7 4/7", "date": "2025-12-01", "exchange": "NMS", "currency": "USD", "gain": 0.006944444444444369, "low_since_signal": 0.0040849673202613505, "high_since_signal": 0.1127450980392156}, "GSL": {"score": "7/7 4/7", "date": "2025-12-01", "exchange": "NYQ", "currency": "USD", "gain": -0.04655075715086923, "low_since_signal": -0.07038698822209753, "high_since_signal": 0.023275378575434814}, "EZPW": {"score": "7/7 6/7", "date": "2025-12-01", "exchange": "NMS", "currency": "USD", "gain": 0.013436692506459845, "low_since_signal": 0.013436692506459845, "high_since_signal": 0.08733850129198954}, "WFRD": {"score": "7/7 5/7", "date": "2025-12-01", "exchange": "NMS", "currency": "USD", "gain": 0.0037804719071829786, "low_since_signal": -0.032981358362664415, "high_since_signal": 0.05996610611393572}}