{"NAT": {"score": "7/7 5/7", "date": "2026-03-31", "exchange": "NYQ", "currency": "USD", "gain": 0.010238907849829284, "low_since_signal": -0.06996587030716725, "high_since_signal": 0.054607508532423105}, "APGE": {"score": "7/7 5/7", "date": "2026-03-31", "exchange": "NGM", "currency": "USD", "gain": -0.013544018058690752, "low_since_signal": -0.040632054176072255, "high_since_signal": 0.09540216229060236}, "PTGX": {"score": "7/7 5/7", "date": "2026-03-31", "exchange": "NGM", "currency": "USD", "gain": -0.057305502846299865, "low_since_signal": -0.07428842504743845, "high_since_signal": 0.00550284629981023}, "ELPC": {"score": "7/7 6/7", "date": "2026-03-31", "exchange": "NYQ", "currency": "USD", "gain": 0.07142857142857142, "low_since_signal": 0.028061224489795925, "high_since_signal": 0.13860544217687082}, "SBS": {"score": "7/7 6/7", "date": "2026-03-31", "exchange": "NYQ", "currency": "USD", "gain": 0.04098360655737705, "low_since_signal": -0.009836065573770428, "high_since_signal": 0.16065573770491812}, "RPRX": {"score": "7/7 6/7", "date": "2026-03-31", "exchange": "NMS", "currency": "USD", "gain": 0.05878674171357099, "low_since_signal": -0.022930998540754668, "high_since_signal": 0.05878674171357099}, "HG": {"score": "7/7 5/7", "date": "2026-03-31", "exchange": "NYQ", "currency": "USD", "gain": 0.03452899765336913, "low_since_signal": 0.004022795843110996, "high_since_signal": 0.09922896413007043}, "BEP": {"score": "7/7 5/7", "date": "2026-03-31", "exchange": "NYQ", "currency": "USD", "gain": 0.042585784313725505, "low_since_signal": -0.01715686274509811, "high_since_signal": 0.08394607843137261}}