{"CYD": {"score": "7/7 4/7", "date": "2025-06-30", "exchange": "NYQ", "currency": "USD", "gain": 0.19113341698034297, "low_since_signal": -0.07444583856127149, "high_since_signal": 0.22751986616478467}, "DRS": {"score": "7/7 5/7", "date": "2025-06-30", "exchange": "NMS", "currency": "USD", "gain": -0.10197934595524946, "low_since_signal": -0.1125215146299483, "high_since_signal": 0.0421686746987952}, "LLYVK": {"score": "7/7 5/7", "date": "2025-06-30", "exchange": "NMS", "currency": "USD", "gain": 0.14810251355347476, "low_since_signal": -0.03745687530803342, "high_since_signal": 0.14810251355347476}, "KEN": {"score": "7/7 5/7", "date": "2025-06-30", "exchange": "NYQ", "currency": "USD", "gain": 0.08158844765342962, "low_since_signal": 0.02839951865222623, "high_since_signal": 0.19157641395908548}, "SBS": {"score": "7/7 6/7", "date": "2025-06-30", "exchange": "NYQ", "currency": "USD", "gain": -0.012289485662266708, "low_since_signal": -0.1288120163859808, "high_since_signal": 0.034592626308602714}, "CTVA": {"score": "7/7 6/7", "date": "2025-06-30", "exchange": "NYQ", "currency": "USD", "gain": -0.03569032604320403, "low_since_signal": -0.048571045216691325, "high_since_signal": 0.03475110693680402}, "MCK": {"score": "7/7 5/7", "date": "2025-06-30", "exchange": "NYQ", "currency": "USD", "gain": -0.08046071126395361, "low_since_signal": -0.10067141570457706, "high_since_signal": 0.0034798984688447668}, "PLNT": {"score": "7/7 4/7", "date": "2025-06-30", "exchange": "NYQ", "currency": "USD", "gain": -0.03860614397065561, "low_since_signal": -0.03860614397065561, "high_since_signal": 0.04126547455295736}}