{"SEZL": {"score": "7/7 5/7", "date": "2025-06-12", "exchange": "NCM", "currency": "USD", "gain": 0.12055674518201295, "low_since_signal": -0.04839400428265526, "high_since_signal": 0.3002141327623127}, "AU": {"score": "7/7 5/7", "date": "2025-06-12", "exchange": "NYQ", "currency": "USD", "gain": 0.08910282671036464, "low_since_signal": -0.10118803768947147, "high_since_signal": 0.08910282671036464}, "ESLT": {"score": "7/7 6/7", "date": "2025-06-12", "exchange": "NMS", "currency": "USD", "gain": 0.13718118313258607, "low_since_signal": -0.019378495671749093, "high_since_signal": 0.13718118313258607}, "SRAD": {"score": "7/7 4/7", "date": "2025-06-12", "exchange": "NMS", "currency": "USD", "gain": 0.1658112909593369, "low_since_signal": -0.03947887879984209, "high_since_signal": 0.1981839715752074}, "DRS": {"score": "7/7 5/7", "date": "2025-06-12", "exchange": "NMS", "currency": "USD", "gain": -0.06712298520644733, "low_since_signal": -0.08147493928019425, "high_since_signal": 0.06955177743431218}, "IMAX": {"score": "7/7 5/7", "date": "2025-06-12", "exchange": "NYQ", "currency": "USD", "gain": -0.11363636363636363, "low_since_signal": -0.11888111888111895, "high_since_signal": 0.022377622377622274}, "HCSG": {"score": "7/7 4/7", "date": "2025-06-12", "exchange": "NMS", "currency": "USD", "gain": -0.06612685560053984, "low_since_signal": -0.14372469635627536, "high_since_signal": 0.04790823211875837}, "ELPC": {"score": "7/7 6/7", "date": "2025-06-12", "exchange": "NYQ", "currency": "USD", "gain": -0.03985507246376802, "low_since_signal": -0.10265700483091784, "high_since_signal": 0.07125603864734298}, "IFS": {"score": "7/7 6/7", "date": "2025-06-12", "exchange": "NYQ", "currency": "USD", "gain": -0.020551649540291997, "low_since_signal": -0.03434288804759319, "high_since_signal": 0.031097890751757864}, "WWD": {"score": "7/7 5/7", "date": "2025-06-12", "exchange": "NMS", "currency": "USD", "gain": 0.10606512023834866, "low_since_signal": -0.01230048946584374, "high_since_signal": 0.1325814002979359}, "NFG": {"score": "7/7 6/7", "date": "2025-06-12", "exchange": "NYQ", "currency": "USD", "gain": 0.04388377376539521, "low_since_signal": -0.017218701422934326, "high_since_signal": 0.06624417075212252}, "KT": {"score": "7/7 6/7", "date": "2025-06-12", "exchange": "NYQ", "currency": "USD", "gain": 0.021361152508693478, "low_since_signal": -0.019374068554396454, "high_since_signal": 0.06209637357178341}, "RPRX": {"score": "7/7 5/7", "date": "2025-06-12", "exchange": "NMS", "currency": "USD", "gain": 0.07400056705415364, "low_since_signal": -0.020130422455344507, "high_since_signal": 0.07400056705415364}}