{"SOFI": {"score": "7/7 4/7", "date": "2025-08-12", "exchange": "NMS", "currency": "USD", "gain": 0.24778012684989442, "low_since_signal": -0.04778012684989425, "high_since_signal": 0.24778012684989442}, "COOP": {"score": "7/7 5/7", "date": "2025-08-12", "exchange": "NCM", "currency": "USD", "gain": 0.11838331160365052, "low_since_signal": -0.04933507170795311, "high_since_signal": 0.15202086049543678}, "FIX": {"score": "7/7 4/7", "date": "2025-08-12", "exchange": "NYQ", "currency": "USD", "gain": 0.11086199693635986, "low_since_signal": -0.05185907255256929, "high_since_signal": 0.11318757833170863}, "TIGO": {"score": "7/7 6/7", "date": "2025-08-12", "exchange": "NMS", "currency": "USD", "gain": 0.1418064812686739, "low_since_signal": 0.011491611123879569, "high_since_signal": 0.1431854746035395}, "IDCC": {"score": "7/7 4/7", "date": "2025-08-12", "exchange": "NMS", "currency": "USD", "gain": 0.2236313135004751, "low_since_signal": -0.05511293034134926, "high_since_signal": 0.23971200935604112}, "FSS": {"score": "7/7 4/7", "date": "2025-08-12", "exchange": "NYQ", "currency": "USD", "gain": -0.03370353231528606, "low_since_signal": -0.058691963597100105, "high_since_signal": -0.0006941230911615256}, "IFS": {"score": "7/7 5/7", "date": "2025-08-12", "exchange": "NYQ", "currency": "USD", "gain": 0.008301886792452787, "low_since_signal": -0.03547169811320746, "high_since_signal": 0.05584905660377355}, "CX": {"score": "7/7 5/7", "date": "2025-08-12", "exchange": "NYQ", "currency": "USD", "gain": 0.034207525655644326, "low_since_signal": -0.03078677309007977, "high_since_signal": 0.08893956670467516}, "AWI": {"score": "7/7 4/7", "date": "2025-08-12", "exchange": "NYQ", "currency": "USD", "gain": 0.012568897130788636, "low_since_signal": -0.0030392005357235017, "high_since_signal": 0.025755936743419357}, "VOD": {"score": "7/7 5/7", "date": "2025-08-12", "exchange": "NMS", "currency": "USD", "gain": -0.011265164644713953, "low_since_signal": -0.011265164644713953, "high_since_signal": 0.04506065857885627}, "GSL": {"score": "7/7 4/7", "date": "2025-08-12", "exchange": "NYQ", "currency": "USD", "gain": 0.05706702057067017, "low_since_signal": -0.027206370272063712, "high_since_signal": 0.09688122096881227}, "TKO": {"score": "7/7 4/7", "date": "2025-08-12", "exchange": "NYQ", "currency": "USD", "gain": 0.08520397150874175, "low_since_signal": -0.018346643643427616, "high_since_signal": 0.10344269371897268}, "ESE": {"score": "7/7 5/7", "date": "2025-08-12", "exchange": "NYQ", "currency": "USD", "gain": 0.06485890431557315, "low_since_signal": -0.07162548243195827, "high_since_signal": 0.09142398877249265}, "SCHW": {"score": "7/7 4/7", "date": "2025-08-12", "exchange": "NYQ", "currency": "USD", "gain": -0.044178741513831186, "low_since_signal": -0.07761677981558412, "high_since_signal": -0.009220792380180328}}