{"IESC": {"score": "7/7 4/7", "date": "2025-09-10", "exchange": "NGM", "currency": "USD", "gain": 0.031139326844880518, "low_since_signal": -0.061596579133765365, "high_since_signal": 0.04934547076261183}, "MRCY": {"score": "7/7 4/7", "date": "2025-09-10", "exchange": "NMS", "currency": "USD", "gain": 0.07447698744769879, "low_since_signal": 0.007531380753137964, "high_since_signal": 0.17154811715481166}, "NEM": {"score": "7/7 5/7", "date": "2025-09-10", "exchange": "NYQ", "currency": "USD", "gain": 0.20986867270177217, "low_since_signal": -0.001402524544179697, "high_since_signal": 0.25296442687747017}, "BZ": {"score": "7/7 4/7", "date": "2025-09-10", "exchange": "NMS", "currency": "USD", "gain": -0.07804068078040677, "low_since_signal": -0.1075134910751349, "high_since_signal": 0.026982150269821443}, "FTI": {"score": "7/7 5/7", "date": "2025-09-10", "exchange": "NYQ", "currency": "USD", "gain": -0.10711665443873813, "low_since_signal": -0.13010516018586452, "high_since_signal": -0.012717045732452999}, "IFS": {"score": "7/7 5/7", "date": "2025-09-10", "exchange": "NYQ", "currency": "USD", "gain": -0.014145288899544556, "low_since_signal": -0.05538240230160638, "high_since_signal": 0.006233517142172093}}