{"BE": {"score": "7/7 4/7", "date": "2026-01-16", "exchange": "NYQ", "currency": "USD", "gain": 0.015050167224080268, "low_since_signal": 0.015050167224080268, "high_since_signal": 0.015050167224080268}, "NGD": {"score": "7/7 4/7", "date": "2026-01-16", "exchange": "ASE", "currency": "USD", "gain": 0.012658227848101156, "low_since_signal": 0.012658227848101156, "high_since_signal": 0.012658227848101156}, "CGAU": {"score": "7/7 4/7", "date": "2026-01-16", "exchange": "NYQ", "currency": "USD", "gain": 0.12213267203967777, "low_since_signal": 0.12213267203967777, "high_since_signal": 0.12213267203967777}, "COMP": {"score": "7/7 4/7", "date": "2026-01-16", "exchange": "NYQ", "currency": "USD", "gain": -0.00777604976671848, "low_since_signal": -0.00777604976671848, "high_since_signal": -0.00777604976671848}, "POWL": {"score": "7/7 5/7", "date": "2026-01-16", "exchange": "NMS", "currency": "USD", "gain": 0.01978665650745274, "low_since_signal": 0.01978665650745274, "high_since_signal": 0.01978665650745274}, "TIGO": {"score": "7/7 5/7", "date": "2026-01-16", "exchange": "NMS", "currency": "USD", "gain": -0.007324135581672623, "low_since_signal": -0.007324135581672623, "high_since_signal": -0.007324135581672623}, "OR": {"score": "7/7 5/7", "date": "2026-01-16", "exchange": "NYQ", "currency": "USD", "gain": 0.06213592233009697, "low_since_signal": 0.06213592233009697, "high_since_signal": 0.06213592233009697}, "BWXT": {"score": "7/7 5/7", "date": "2026-01-16", "exchange": "NYQ", "currency": "USD", "gain": -0.05424755610629214, "low_since_signal": -0.05424755610629214, "high_since_signal": -0.05424755610629214}, "MTZ": {"score": "7/7 5/7", "date": "2026-01-16", "exchange": "NYQ", "currency": "USD", "gain": -0.008088811852585564, "low_since_signal": -0.008088811852585564, "high_since_signal": -0.008088811852585564}, "APG": {"score": "7/7 6/7", "date": "2026-01-16", "exchange": "NYQ", "currency": "USD", "gain": -0.018449322746380177, "low_since_signal": -0.018449322746380177, "high_since_signal": -0.018449322746380177}, "CWK": {"score": "7/7 5/7", "date": "2026-01-16", "exchange": "NYQ", "currency": "USD", "gain": -0.037790697674418526, "low_since_signal": -0.037790697674418526, "high_since_signal": -0.037790697674418526}}