{"WLDN": {"score": "7/7 4/7", "date": "2026-01-27", "exchange": "NGM", "currency": "USD", "gain": -0.38506002667852374, "low_since_signal": -0.3903957314361938, "high_since_signal": -0.008003557136504996}, "TER": {"score": "7/7 4/7", "date": "2026-01-27", "exchange": "NMS", "currency": "USD", "gain": 0.14323396416010722, "low_since_signal": 0.008834366102830284, "high_since_signal": 0.4353542120247864}, "MKSI": {"score": "7/7 4/7", "date": "2026-01-27", "exchange": "NMS", "currency": "USD", "gain": -0.08448862150143864, "low_since_signal": -0.08448862150143864, "high_since_signal": 0.14521754294184325}, "FIX": {"score": "7/7 4/7", "date": "2026-01-27", "exchange": "NYQ", "currency": "USD", "gain": 0.10284709168980322, "low_since_signal": -0.03496352756557274, "high_since_signal": 0.26560209694942144}, "ENS": {"score": "7/7 5/7", "date": "2026-01-27", "exchange": "NYQ", "currency": "USD", "gain": -0.13758407915948637, "low_since_signal": -0.13758407915948637, "high_since_signal": 0.05581188504085842}, "POWL": {"score": "7/7 5/7", "date": "2026-01-27", "exchange": "NMS", "currency": "USD", "gain": 0.09405750220553302, "low_since_signal": -0.004343203565046296, "high_since_signal": 0.34053430452190836}, "PRIM": {"score": "7/7 4/7", "date": "2026-01-27", "exchange": "NYQ", "currency": "USD", "gain": -0.12366723706726335, "low_since_signal": -0.12366723706726335, "high_since_signal": 0.1146505199420825}, "CHRW": {"score": "7/7 5/7", "date": "2026-01-27", "exchange": "NMS", "currency": "USD", "gain": -0.0009454424114343803, "low_since_signal": -0.07007396696512982, "high_since_signal": 0.11178466158723094}, "AMRX": {"score": "7/7 4/7", "date": "2026-01-27", "exchange": "NMS", "currency": "USD", "gain": -0.042660882140274754, "low_since_signal": -0.042660882140274754, "high_since_signal": 0.09833694866232823}, "MLI": {"score": "7/7 7/7", "date": "2026-01-27", "exchange": "NYQ", "currency": "USD", "gain": -0.14736293981998067, "low_since_signal": -0.14736293981998067, "high_since_signal": 0.03533437476753701}, "EC": {"score": "7/7 6/7", "date": "2026-01-27", "exchange": "NYQ", "currency": "USD", "gain": -0.012232415902140683, "low_since_signal": -0.11391437308868503, "high_since_signal": -0.012232415902140683}, "MFG": {"score": "7/7 5/7", "date": "2026-01-27", "exchange": "NYQ", "currency": "USD", "gain": -0.07142857142857134, "low_since_signal": -0.07142857142857134, "high_since_signal": 0.16244239631336407}, "DB": {"score": "7/7 5/7", "date": "2026-01-27", "exchange": "NYQ", "currency": "USD", "gain": -0.22514257376642693, "low_since_signal": -0.22514257376642693, "high_since_signal": -0.011901810066947604}, "HE": {"score": "7/7 4/7", "date": "2026-01-27", "exchange": "NYQ", "currency": "USD", "gain": -0.031168831168831197, "low_since_signal": -0.031168831168831197, "high_since_signal": 0.10909090909090896}, "PUK": {"score": "7/7 6/7", "date": "2026-01-27", "exchange": "NYQ", "currency": "USD", "gain": -0.11840097650289906, "low_since_signal": -0.11840097650289906, "high_since_signal": 0.025633201098565647}, "INVX": {"score": "7/7 4/7", "date": "2026-01-27", "exchange": "NYQ", "currency": "USD", "gain": 0.04906094288999621, "low_since_signal": -0.07665772326561901, "high_since_signal": 0.12111920275967804}, "ELPC": {"score": "7/7 6/7", "date": "2026-01-27", "exchange": "NYQ", "currency": "USD", "gain": 0.04143126177024494, "low_since_signal": -0.059322033898304996, "high_since_signal": 0.10169491525423731}, "PAC": {"score": "7/7 7/7", "date": "2026-01-27", "exchange": "NYQ", "currency": "USD", "gain": -0.16287518075688634, "low_since_signal": -0.16287518075688634, "high_since_signal": 0.05953514619264295}, "UBS": {"score": "7/7 5/7", "date": "2026-01-27", "exchange": "NYQ", "currency": "USD", "gain": -0.21949238578680208, "low_since_signal": -0.21949238578680208, "high_since_signal": -0.022131979695431542}, "NWG": {"score": "7/7 5/7", "date": "2026-01-27", "exchange": "NYQ", "currency": "USD", "gain": -0.151912568306011, "low_since_signal": -0.151912568306011, "high_since_signal": 0.04207650273224041}, "TLK": {"score": "7/7 5/7", "date": "2026-01-27", "exchange": "NYQ", "currency": "USD", "gain": -0.17925736235595388, "low_since_signal": -0.17925736235595388, "high_since_signal": -0.07597097737942814}}