{"VSAT": {"score": "7/7 4/7", "date": "2026-01-28", "exchange": "NMS", "currency": "USD", "gain": -0.025010508617065948, "low_since_signal": -0.21311475409836067, "high_since_signal": 0.09541824295922655}, "UEC": {"score": "7/7 4/7", "date": "2026-01-28", "exchange": "ASE", "currency": "USD", "gain": -0.3997020854021847, "low_since_signal": -0.3997020854021847, "high_since_signal": -0.07646474677259181}, "BKD": {"score": "7/7 4/7", "date": "2026-01-28", "exchange": "NYQ", "currency": "USD", "gain": 0.04805491990846688, "low_since_signal": 0.04805491990846688, "high_since_signal": 0.27917620137299776}, "TEVA": {"score": "7/7 5/7", "date": "2026-01-28", "exchange": "NYQ", "currency": "USD", "gain": -0.13489912676904547, "low_since_signal": -0.13971695272508283, "high_since_signal": 0.0915386931647094}, "CX": {"score": "7/7 5/7", "date": "2026-01-28", "exchange": "NYQ", "currency": "USD", "gain": -0.2397260273972603, "low_since_signal": -0.2397260273972603, "high_since_signal": -0.017503805175038082}, "CMRE": {"score": "7/7 4/7", "date": "2026-01-28", "exchange": "NYQ", "currency": "USD", "gain": 0.014519056261342917, "low_since_signal": -0.0568663036902602, "high_since_signal": 0.08348457350272226}, "NVT": {"score": "7/7 5/7", "date": "2026-01-28", "exchange": "NYQ", "currency": "USD", "gain": 0.0188348664038545, "low_since_signal": -0.071222076215506, "high_since_signal": 0.07385019710906694}, "CW": {"score": "7/7 6/7", "date": "2026-01-28", "exchange": "NYQ", "currency": "USD", "gain": 0.010128525419137372, "low_since_signal": -0.06901845107305182, "high_since_signal": 0.09333895193089121}, "INSW": {"score": "7/7 4/7", "date": "2026-01-28", "exchange": "NYQ", "currency": "USD", "gain": 0.17072749265595305, "low_since_signal": -0.01745291169863484, "high_since_signal": 0.28218420597891836}, "WCC": {"score": "7/7 4/7", "date": "2026-01-28", "exchange": "NYQ", "currency": "USD", "gain": -0.14002682901661337, "low_since_signal": -0.14002682901661337, "high_since_signal": 0.08231004712275997}, "RBC": {"score": "7/7 5/7", "date": "2026-01-28", "exchange": "NYQ", "currency": "USD", "gain": 0.04354062285096773, "low_since_signal": -0.01823361823361818, "high_since_signal": 0.14920915610570784}, "LFUS": {"score": "7/7 5/7", "date": "2026-01-28", "exchange": "NMS", "currency": "USD", "gain": 0.02257869056351049, "low_since_signal": -0.03600471983927041, "high_since_signal": 0.201294766718755}}