{"SSRM": {"score": "7/7 4/7", "date": "2025-10-15", "exchange": "NMS", "currency": "USD", "gain": -0.09759937032664306, "low_since_signal": -0.1290830381739473, "high_since_signal": 0.015348288075560825}, "IAG": {"score": "7/7 5/7", "date": "2025-10-15", "exchange": "NYQ", "currency": "USD", "gain": -0.18232819074333798, "low_since_signal": -0.19424964936886394, "high_since_signal": 0.026647966339410994}, "INDV": {"score": "7/7 4/7", "date": "2025-10-15", "exchange": "NMS", "currency": "USD", "gain": 0.15641127431520435, "low_since_signal": -0.04366812227074241, "high_since_signal": 0.15641127431520435}, "ARMN": {"score": "7/7 4/7", "date": "2025-10-15", "exchange": "ASE", "currency": "USD", "gain": -0.08514492753623185, "low_since_signal": -0.17663043478260865, "high_since_signal": -0.007246376811594049}, "BTG": {"score": "7/7 6/7", "date": "2025-10-15", "exchange": "ASE", "currency": "USD", "gain": -0.14109347442680772, "low_since_signal": -0.1587301587301588, "high_since_signal": 0.0476190476190477}, "MOD": {"score": "7/7 4/7", "date": "2025-10-15", "exchange": "NYQ", "currency": "USD", "gain": -0.05472943789720494, "low_since_signal": -0.08496328746837775, "high_since_signal": 0.005861664712778535}, "CX": {"score": "7/7 6/7", "date": "2025-10-15", "exchange": "NYQ", "currency": "USD", "gain": 0.03051881993896243, "low_since_signal": -0.0681586978636826, "high_since_signal": 0.046795523906408856}, "FLEX": {"score": "7/7 6/7", "date": "2025-10-15", "exchange": "NMS", "currency": "USD", "gain": 0.006132075471698122, "low_since_signal": -0.03569182389937112, "high_since_signal": 0.03930817610062882}, "PTCT": {"score": "7/7 5/7", "date": "2025-10-15", "exchange": "NMS", "currency": "USD", "gain": -0.005838563713326604, "low_since_signal": -0.03736680776528977, "high_since_signal": -0.0021894613924975286}, "NVT": {"score": "7/7 4/7", "date": "2025-10-15", "exchange": "NYQ", "currency": "USD", "gain": 0.034192269573835365, "low_since_signal": -0.03934588701684835, "high_since_signal": 0.05332011892963325}, "POWL": {"score": "7/7 4/7", "date": "2025-10-15", "exchange": "NMS", "currency": "USD", "gain": 0.14534813197476956, "low_since_signal": 0.0028808830664725517, "high_since_signal": 0.23838549247937899}, "DY": {"score": "7/7 5/7", "date": "2025-10-15", "exchange": "NYQ", "currency": "USD", "gain": -0.041697342882002476, "low_since_signal": -0.064587377016264, "high_since_signal": -0.008399705508332746}}