{"SBSW": {"score": "7/7 5/7", "date": "2026-01-06", "exchange": "NYQ", "currency": "USD", "gain": 0.06732550957381098, "low_since_signal": -0.05373687461395929, "high_since_signal": 0.08276714021000617}, "AU": {"score": "7/7 4/7", "date": "2026-01-06", "exchange": "NYQ", "currency": "USD", "gain": 0.14072175955584035, "low_since_signal": -0.02775998291693353, "high_since_signal": 0.14072175955584035}, "NGD": {"score": "7/7 4/7", "date": "2026-01-06", "exchange": "ASE", "currency": "USD", "gain": 0.1764705882352941, "low_since_signal": -0.016806722689075647, "high_since_signal": 0.1764705882352941}, "PSLV": {"score": "7/7 6/7", "date": "2026-01-06", "exchange": "ASE", "currency": "USD", "gain": 0.152214365463342, "low_since_signal": -0.05173055452177151, "high_since_signal": 0.152214365463342}, "KGC": {"score": "7/7 4/7", "date": "2026-01-06", "exchange": "NYQ", "currency": "USD", "gain": 0.2030273116156631, "low_since_signal": 0.004935834155972312, "high_since_signal": 0.2030273116156631}, "GFI": {"score": "7/7 5/7", "date": "2026-01-06", "exchange": "NYQ", "currency": "USD", "gain": 0.12007623888182978, "low_since_signal": -0.03515459551037689, "high_since_signal": 0.12007623888182978}, "PAAS": {"score": "7/7 4/7", "date": "2026-01-06", "exchange": "NYQ", "currency": "USD", "gain": 0.056025941271842905, "low_since_signal": -0.0435957485137812, "high_since_signal": 0.056025941271842905}, "NEM": {"score": "7/7 4/7", "date": "2026-01-06", "exchange": "NYQ", "currency": "USD", "gain": 0.08919413919413914, "low_since_signal": -0.021153846153846176, "high_since_signal": 0.08919413919413914}, "BELFB": {"score": "7/7 4/7", "date": "2026-01-06", "exchange": "NMS", "currency": "USD", "gain": 0.09373131082477018, "low_since_signal": -0.020442559669439565, "high_since_signal": 0.09373131082477018}, "SQM": {"score": "7/7 4/7", "date": "2026-01-06", "exchange": "NYQ", "currency": "USD", "gain": 0.07540587682812297, "low_since_signal": -0.0063061854286864194, "high_since_signal": 0.11606064671944191}, "EGO": {"score": "7/7 4/7", "date": "2026-01-06", "exchange": "NYQ", "currency": "USD", "gain": 0.13465608465608475, "low_since_signal": 0.003174603174603295, "high_since_signal": 0.13465608465608475}, "GILT": {"score": "7/7 5/7", "date": "2026-01-06", "exchange": "NMS", "currency": "USD", "gain": 0.1733067729083666, "low_since_signal": -0.031208499335989418, "high_since_signal": 0.1859229747675962}, "BVN": {"score": "7/7 5/7", "date": "2026-01-06", "exchange": "NYQ", "currency": "USD", "gain": 0.24717982747179837, "low_since_signal": 0.01990710019907093, "high_since_signal": 0.24717982747179837}, "BELFA": {"score": "7/7 4/7", "date": "2026-01-06", "exchange": "NMS", "currency": "USD", "gain": 0.11711272328232646, "low_since_signal": -0.028287508382613027, "high_since_signal": 0.11711272328232646}, "TEVA": {"score": "7/7 5/7", "date": "2026-01-06", "exchange": "NYQ", "currency": "USD", "gain": -0.023357209592027407, "low_since_signal": -0.023357209592027407, "high_since_signal": 0.021177203363438174}, "ELAN": {"score": "7/7 5/7", "date": "2026-01-06", "exchange": "NYQ", "currency": "USD", "gain": 0.015126050420168043, "low_since_signal": -0.04033613445378155, "high_since_signal": 0.03067226890756304}, "EXPE": {"score": "7/7 4/7", "date": "2026-01-06", "exchange": "NMS", "currency": "USD", "gain": -0.0904381538050199, "low_since_signal": -0.0904381538050199, "high_since_signal": 0.007018482002606941}, "DLTR": {"score": "7/7 5/7", "date": "2026-01-06", "exchange": "NMS", "currency": "USD", "gain": 0.0020929884885633214, "low_since_signal": -0.01659440873075197, "high_since_signal": 0.0555389445358051}, "REVG": {"score": "7/7 4/7", "date": "2026-01-06", "exchange": "NYQ", "currency": "USD", "gain": 0.006822316555488218, "low_since_signal": -0.013644633110976221, "high_since_signal": 0.03926622195269866}, "WPM": {"score": "7/7 4/7", "date": "2026-01-06", "exchange": "NYQ", "currency": "USD", "gain": 0.12883435582822086, "low_since_signal": -0.02007808142777476, "high_since_signal": 0.12883435582822086}, "LAUR": {"score": "7/7 5/7", "date": "2026-01-06", "exchange": "NMS", "currency": "USD", "gain": -0.012202043132803623, "low_since_signal": -0.01958002270147573, "high_since_signal": 0.009364358683314367}, "MRCY": {"score": "7/7 5/7", "date": "2026-01-06", "exchange": "NMS", "currency": "USD", "gain": 0.15252225519287826, "low_since_signal": 0.006528189910979195, "high_since_signal": 0.22278931750741834}, "RKT": {"score": "7/7 4/7", "date": "2026-01-06", "exchange": "NYQ", "currency": "USD", "gain": 0.0396039603960396, "low_since_signal": 0.0014144271570013004, "high_since_signal": 0.10513908533710516}, "HTHT": {"score": "7/7 6/7", "date": "2026-01-06", "exchange": "NMS", "currency": "USD", "gain": -0.04420432220039293, "low_since_signal": -0.054616895874263285, "high_since_signal": 0.000589390962671928}, "VALE": {"score": "7/7 4/7", "date": "2026-01-06", "exchange": "NYQ", "currency": "USD", "gain": 0.053634438955539855, "low_since_signal": -0.019054340155257556, "high_since_signal": 0.053634438955539855}, "MTZ": {"score": "7/7 5/7", "date": "2026-01-06", "exchange": "NYQ", "currency": "USD", "gain": 0.01692405331076793, "low_since_signal": -0.07378887243494817, "high_since_signal": 0.025216839433044248}, "RGLD": {"score": "7/7 6/7", "date": "2026-01-06", "exchange": "NMS", "currency": "USD", "gain": 0.13625204582651385, "low_since_signal": -0.006873977086743072, "high_since_signal": 0.13625204582651385}, "BFH": {"score": "7/7 4/7", "date": "2026-01-06", "exchange": "NYQ", "currency": "USD", "gain": -0.1285821081485174, "low_since_signal": -0.14029404435584356, "high_since_signal": 0.01233491153750305}, "APG": {"score": "7/7 5/7", "date": "2026-01-06", "exchange": "NYQ", "currency": "USD", "gain": 0.020641087906750885, "low_since_signal": -0.01675570665371534, "high_since_signal": 0.03982515784361342}, "UAL": {"score": "7/7 5/7", "date": "2026-01-06", "exchange": "NMS", "currency": "USD", "gain": -0.07623585467540209, "low_since_signal": -0.07623585467540209, "high_since_signal": -0.0017867778439548026}, "MGA": {"score": "7/7 4/7", "date": "2026-01-06", "exchange": "NYQ", "currency": "USD", "gain": -0.05447813822284902, "low_since_signal": -0.05447813822284902, "high_since_signal": 0.004760225669957742}, "EZPW": {"score": "7/7 5/7", "date": "2026-01-06", "exchange": "NMS", "currency": "USD", "gain": -0.014425314099581142, "low_since_signal": -0.014425314099581142, "high_since_signal": 0.01954397394136816}, "ORA": {"score": "7/7 6/7", "date": "2026-01-06", "exchange": "NYQ", "currency": "USD", "gain": 0.009957081545064349, "low_since_signal": -0.021287553648068704, "high_since_signal": 0.033905579399141655}, "ROK": {"score": "7/7 5/7", "date": "2026-01-06", "exchange": "NYQ", "currency": "USD", "gain": -0.022643700406425424, "low_since_signal": -0.023466227985291244, "high_since_signal": 0.018797174375846677}, "ATMU": {"score": "7/7 4/7", "date": "2026-01-06", "exchange": "NYQ", "currency": "USD", "gain": 0.024358737774497145, "low_since_signal": -0.026388632589038563, "high_since_signal": 0.05572983945377382}, "RBC": {"score": "7/7 5/7", "date": "2026-01-06", "exchange": "NYQ", "currency": "USD", "gain": 0.041181416859365216, "low_since_signal": -0.01751103636745845, "high_since_signal": 0.0486020601219256}, "KAR": {"score": "7/7 4/7", "date": "2026-01-06", "exchange": "NYQ", "currency": "USD", "gain": -0.05226480836236929, "low_since_signal": -0.05226480836236929, "high_since_signal": -0.008552423186569515}, "LNC": {"score": "7/7 5/7", "date": "2026-01-06", "exchange": "NYQ", "currency": "USD", "gain": -0.1354936929099608, "low_since_signal": -0.1354936929099608, "high_since_signal": -0.038277511961722445}, "ADI": {"score": "7/7 5/7", "date": "2026-01-06", "exchange": "NMS", "currency": "USD", "gain": 0.009319314535399803, "low_since_signal": -0.00017068341639930147, "high_since_signal": 0.031269201884345}}