{"LITE": {"score": "7/7 4/7", "date": "2026-02-12", "exchange": "NMS", "currency": "USD", "gain": 0.08943200904946345, "low_since_signal": -0.035512288760154984, "high_since_signal": 0.08943200904946345}, "PRAX": {"score": "7/7 4/7", "date": "2026-02-12", "exchange": "NMS", "currency": "USD", "gain": -0.003934879250270342, "low_since_signal": -0.04706836477231772, "high_since_signal": -0.003934879250270342}, "CLMT": {"score": "7/7 4/7", "date": "2026-02-12", "exchange": "NMS", "currency": "USD", "gain": 0.13125481139337952, "low_since_signal": 0.10123171670515778, "high_since_signal": 0.1354888375673595}}