{"ARWR": {"score": "7/7 4/7", "date": "2026-02-02", "exchange": "NMS", "currency": "USD", "gain": -0.0676712328767123, "low_since_signal": -0.0676712328767123, "high_since_signal": -0.011780821917808212}, "HLF": {"score": "7/7 4/7", "date": "2026-02-02", "exchange": "NYQ", "currency": "USD", "gain": -0.027586206896551547, "low_since_signal": -0.027586206896551547, "high_since_signal": -0.02643678160919525}, "AAMI": {"score": "7/7 4/7", "date": "2026-02-02", "exchange": "NYQ", "currency": "USD", "gain": -0.0598030438675023, "low_since_signal": -0.0748433303491495, "high_since_signal": -0.0598030438675023}, "ECO": {"score": "7/7 6/7", "date": "2026-02-02", "exchange": "NYQ", "currency": "USD", "gain": -0.035009861932938896, "low_since_signal": -0.035009861932938896, "high_since_signal": 0.0088757396449704}, "INSW": {"score": "7/7 4/7", "date": "2026-02-02", "exchange": "NYQ", "currency": "USD", "gain": -0.023517721099701915, "low_since_signal": -0.023517721099701915, "high_since_signal": 0.010599536270288184}, "NHC": {"score": "7/7 5/7", "date": "2026-02-02", "exchange": "ASE", "currency": "USD", "gain": 0.014468484158349499, "low_since_signal": -0.0026793489182129126, "high_since_signal": 0.014468484158349499}, "VTRS": {"score": "7/7 5/7", "date": "2026-02-02", "exchange": "NMS", "currency": "USD", "gain": 0.04970760233918127, "low_since_signal": 0.0, "high_since_signal": 0.04970760233918127}, "CPA": {"score": "7/7 5/7", "date": "2026-02-02", "exchange": "NYQ", "currency": "USD", "gain": 0.03790128694668374, "low_since_signal": 0.030052326403620423, "high_since_signal": 0.03790128694668374}}