{"PRAX": {"score": "7/7 4/7", "date": "2026-02-20", "exchange": "NMS", "currency": "USD", "gain": -0.050882844189930644, "low_since_signal": -0.050882844189930644, "high_since_signal": 0.03659627773801014}, "TER": {"score": "7/7 4/7", "date": "2026-02-20", "exchange": "NMS", "currency": "USD", "gain": -0.06350623364629827, "low_since_signal": -0.06350623364629827, "high_since_signal": 0.0553178390026165}, "TPC": {"score": "7/7 4/7", "date": "2026-02-20", "exchange": "NYQ", "currency": "USD", "gain": -0.1950517836593786, "low_since_signal": -0.1950517836593786, "high_since_signal": 0.02853855005753728}, "MOD": {"score": "7/7 4/7", "date": "2026-02-20", "exchange": "NYQ", "currency": "USD", "gain": -0.062025092772574744, "low_since_signal": -0.062025092772574744, "high_since_signal": 0.05363138363668486}, "FN": {"score": "7/7 5/7", "date": "2026-02-20", "exchange": "NYQ", "currency": "USD", "gain": 0.012634354457729802, "low_since_signal": -0.000915532931719554, "high_since_signal": 0.1279182612198561}, "CGON": {"score": "7/7 4/7", "date": "2026-02-20", "exchange": "NMS", "currency": "USD", "gain": 0.05066805483255239, "low_since_signal": -0.026375151830643814, "high_since_signal": 0.05066805483255239}, "IESC": {"score": "7/7 4/7", "date": "2026-02-20", "exchange": "NGM", "currency": "USD", "gain": -0.061769969403659954, "low_since_signal": -0.061769969403659954, "high_since_signal": -0.00889025727865762}, "PRIM": {"score": "7/7 4/7", "date": "2026-02-20", "exchange": "NYQ", "currency": "USD", "gain": -0.13155408597071327, "low_since_signal": -0.13155408597071327, "high_since_signal": -0.021965044874823023}, "DY": {"score": "7/7 4/7", "date": "2026-02-20", "exchange": "NYQ", "currency": "USD", "gain": -0.06106159681660579, "low_since_signal": -0.06106159681660579, "high_since_signal": -0.0026760989458497987}, "AGI": {"score": "7/7 4/7", "date": "2026-02-20", "exchange": "NYQ", "currency": "USD", "gain": 0.09218227424749156, "low_since_signal": 0.038879598662207346, "high_since_signal": 0.15656354515050155}, "XPO": {"score": "7/7 4/7", "date": "2026-02-20", "exchange": "NYQ", "currency": "USD", "gain": 0.02620669938533378, "low_since_signal": -0.05422404345547241, "high_since_signal": 0.02620669938533378}, "KB": {"score": "7/7 6/7", "date": "2026-02-20", "exchange": "NYQ", "currency": "USD", "gain": -0.10088390277069514, "low_since_signal": -0.10088390277069514, "high_since_signal": 0.004674485806561254}, "UGP": {"score": "7/7 5/7", "date": "2026-02-20", "exchange": "NYQ", "currency": "USD", "gain": -0.10654205607476624, "low_since_signal": -0.10654205607476624, "high_since_signal": 0.0018691588785047992}, "EME": {"score": "7/7 4/7", "date": "2026-02-20", "exchange": "NYQ", "currency": "USD", "gain": -0.09410794916276038, "low_since_signal": -0.10847820470232158, "high_since_signal": -0.00736967728441542}, "HWM": {"score": "7/7 4/7", "date": "2026-02-20", "exchange": "NYQ", "currency": "USD", "gain": 0.0028671057729560334, "low_since_signal": -0.004106935296396754, "high_since_signal": 0.027160015497869006}, "BBD": {"score": "7/7 6/7", "date": "2026-02-20", "exchange": "NYQ", "currency": "USD", "gain": -0.09069212410501201, "low_since_signal": -0.09069212410501201, "high_since_signal": -0.01670644391408121}, "BBDO": {"score": "7/7 6/7", "date": "2026-02-20", "exchange": "NYQ", "currency": "USD", "gain": -0.06631299734748011, "low_since_signal": -0.06631299734748011, "high_since_signal": -0.00795755968169756}, "WLFC": {"score": "7/7 4/7", "date": "2026-02-20", "exchange": "NGM", "currency": "USD", "gain": -0.06559134545100145, "low_since_signal": -0.06559134545100145, "high_since_signal": 0.0001461917060572152}, "JBL": {"score": "7/7 5/7", "date": "2026-02-20", "exchange": "NYQ", "currency": "USD", "gain": -0.06215647939798579, "low_since_signal": -0.06215647939798579, "high_since_signal": 0.02390350068243026}, "JOE": {"score": "7/7 4/7", "date": "2026-02-20", "exchange": "NYQ", "currency": "USD", "gain": 0.017757270693512447, "low_since_signal": -0.03635346756152118, "high_since_signal": 0.017757270693512447}, "AES": {"score": "7/7 4/7", "date": "2026-02-20", "exchange": "NYQ", "currency": "USD", "gain": -0.14112658994548768, "low_since_signal": -0.14112658994548768, "high_since_signal": 0.0466384009691096}, "AVT": {"score": "7/7 5/7", "date": "2026-02-20", "exchange": "NMS", "currency": "USD", "gain": -0.05273321449792024, "low_since_signal": -0.05273321449792024, "high_since_signal": 0.00029708853238280205}, "SBS": {"score": "7/7 7/7", "date": "2026-02-20", "exchange": "NYQ", "currency": "USD", "gain": -0.05428186109238029, "low_since_signal": -0.05428186109238029, "high_since_signal": 0.028658125421443068}}